LICENSE.md
MANIFEST.in
README.md
setup.py
drf_auto_endpoint/__init__.py
drf_auto_endpoint/adapters.py
drf_auto_endpoint/app_settings.py
drf_auto_endpoint/apps.py
drf_auto_endpoint/decorators.py
drf_auto_endpoint/endpoints.py
drf_auto_endpoint/factories.py
drf_auto_endpoint/get_field_dict.py
drf_auto_endpoint/metadata.py
drf_auto_endpoint/router.py
drf_auto_endpoint/utils.py
drf_schema_adapter.egg-info/PKG-INFO
drf_schema_adapter.egg-info/SOURCES.txt
drf_schema_adapter.egg-info/dependency_links.txt
drf_schema_adapter.egg-info/requires.txt
drf_schema_adapter.egg-info/top_level.txt
export_app/__init__.py
export_app/adapters.py
export_app/base.py
export_app/urls.py
export_app/views.py
export_app/management/__init__.py
export_app/management/commands/__init__.py
export_app/management/commands/export.py
export_app/management/commands/export_wizard.py
export_app/management/commands/reexport.py
export_app/templates/export_app/angular2_model.ts
export_app/templates/export_app/angular2_model_base.ts
export_app/templates/export_app/angular2_service.ts
export_app/templates/export_app/angular2_service_base.ts
export_app/templates/export_app/angular_resource.js
export_app/templates/export_app/dynamic_model.js
export_app/templates/export_app/ember_metadata.js
export_app/templates/export_app/ember_metadata_index.js
export_app/templates/export_app/ember_model.js
export_app/templates/export_app/ember_model_base.js
export_app/templates/export_app/ember_model_test.js
export_app/templates/export_app/mobxaxios_base_model.js
export_app/templates/export_app/mobxaxios_base_store.js
export_app/templates/export_app/mobxaxios_config.js
export_app/templates/export_app/mobxaxios_model.js
export_app/templates/export_app/mobxaxios_model_base.js
export_app/templates/export_app/mobxaxios_store.js
export_app/templates/export_app/vuexorm_axios_base_model.js
export_app/templates/export_app/vuexorm_axios_database.js
export_app/templates/export_app/vuexorm_axios_http.js
export_app/templates/export_app/vuexorm_axios_model.js
export_app/templates/export_app/vuexorm_axios_model_base.js