Metadata-Version: 2.1
Name: drf-schema-adapter
Version: 3.0.6
Summary: Making using Django with frontend libraries and frameworks DRYer
Home-page: https://github.com/drf-forms/drf-schema-adapter
Author: Emmanuelle Delescolle, Adrien Brunet, Mauro Bianchi, Mattia Larentis, Aaron Elliot Ross
Author-email: info@levit.be
License: MIT License
Classifier: Environment :: Web Environment
Classifier: Framework :: Django
Classifier: Framework :: Django :: 3.2
Classifier: Framework :: Django :: 4.0
Classifier: Framework :: Django :: 4.1
Classifier: Intended Audience :: Developers
Classifier: License :: OSI Approved :: MIT License
Classifier: Operating System :: OS Independent
Classifier: Programming Language :: Python
Classifier: Programming Language :: Python :: 3
Classifier: Programming Language :: Python :: 3.8
Classifier: Programming Language :: Python :: 3.9
Classifier: Programming Language :: Python :: 3.10
Classifier: Topic :: Internet :: WWW/HTTP
Classifier: Topic :: Internet :: WWW/HTTP :: Dynamic Content
License-File: LICENSE.md
